norite/__init__.py
norite/console.py
norite/version.py
norite/core/Page.py
norite/core/__init__.py
norite/core/builder.py
norite/core/env.py
norite/core/toml.py
norite/utils/__init__.py
norite/utils/init.py
norite/utils/print_helpers.py
norite/utils/robots_txt.py
norite/utils/rss.py
norite/utils/sass.py
norite/utils/server.py
norite/utils/sitemap.py
norite-0.2.2.dist-info/LICENSE.txt
norite-0.2.2.dist-info/METADATA
norite-0.2.2.dist-info/WHEEL
norite-0.2.2.dist-info/entry_points.txt
norite-0.2.2.dist-info/top_level.txt
norite-0.2.2.dist-info/RECORD
