Metadata-Version: 2.1
Name: norite
Version: 0.2.2
Summary: A simple static website generator powered by Jinja2
Home-page: https://github.com/prdx23/norite
Author: Arsh
Author-email: hi@prdx.me
Project-URL: Source, https://github.com/prdx23/norite
Project-URL: Tracker, https://github.com/prdx23/norite/issues
Project-URL: Documentation, https://github.com/prdx23/norite/wiki
Keywords: static web site generator SSG jinja jinja2 markdown
Classifier: Programming Language :: Python :: 3
Classifier: Programming Language :: Python :: 3.6
Classifier: Programming Language :: Python :: 3.7
Classifier: Programming Language :: Python :: 3.8
Classifier: Programming Language :: Python :: 3.9
Classifier: Programming Language :: Python :: 3.10
Classifier: License :: OSI Approved :: MIT License
Classifier: Operating System :: OS Independent
Classifier: Development Status :: 3 - Alpha
Classifier: Environment :: Console
Classifier: Environment :: Web Environment
Classifier: Topic :: Internet :: WWW/HTTP
Classifier: Topic :: Text Processing :: Markup :: Markdown
Classifier: Topic :: Text Processing :: Markup :: HTML
Requires-Python: >=3.6
License-File: LICENSE.txt
Requires-Dist: toml
Requires-Dist: jinja2
Requires-Dist: markdown
Requires-Dist: watchdog
Requires-Dist: pygments
